LICENSE
README.md
setup.py
melctl_client/__init__.py
melctl_client/__main__.py
melctl_client/commands.py
melctl_client/config.py
melctl_client/hints.py
melctl_client.egg-info/PKG-INFO
melctl_client.egg-info/SOURCES.txt
melctl_client.egg-info/dependency_links.txt
melctl_client.egg-info/entry_points.txt
melctl_client.egg-info/requires.txt
melctl_client.egg-info/top_level.txt
melctl_client/utils/__init__.py
melctl_client_plugins/builtins/__init__.py
melctl_client_plugins/builtins/complete.py
melctl_client_plugins/builtins/conf.py
melctl_client_plugins/builtins/login.py
melctl_client_plugins/builtins/ping.py
melctl_client_plugins/builtins/version.py