Metadata-Version: 2.1
Name: melctl-client
Version: 5.5.1
Summary: Command-line client for LuxProvide API (MelCtl)
Home-page: https://github.com/LuxProvide/melctl-client
Author: jpclipffel
License-File: LICENSE
